<?xml version="1.0"?>
<opencv_storage>
<stage6>
  <maxWeakCount>7</maxWeakCount>
  <stageThreshold>-1.6176511049270630e+00</stageThreshold>
  <weakClassifiers>
    <_>
      <internalNodes>
        0 -1 15840 -1187832327 -865370241 -272629891 -67731587
        -1761675393 -1393066121 -54607890 -1352512015</internalNodes>
      <leafValues>
        -4.3030303716659546e-01 7.2765958309173584e-01</leafValues></_>
    <_>
      <internalNodes>
        0 -1 12871 -1725415300 -1785683117 320864276 -1860685419
        -1500725042 -1159626690 -662665266 -913511734</internalNodes>
      <leafValues>
        -6.5153491497039795e-01 5.2211821079254150e-01</leafValues></_>
    <_>
      <internalNodes>
        0 -1 15095 -1422172676 -42631820 -1074299013 -575243011
        -1879640203 -8585873 -1644232961 -416907013</internalNodes>
      <leafValues>
        -5.2836114168167114e-01 6.2996119260787964e-01</leafValues></_>
    <_>
      <internalNodes>
        0 -1 11523 -2139013052 -1073086399 1343477971 -262336235
        1048576513 1325466176 -1198654273 412088015</internalNodes>
      <leafValues>
        -8.3295106887817383e-01 4.0264198184013367e-01</leafValues></_>
    <_>
      <internalNodes>
        0 -1 15695 -143045592 -425636616 -1124270108 -720909241
        -141539704 -193897136 -193931574 -5567346</internalNodes>
      <leafValues>
        -4.2436677217483521e-01 8.0226075649261475e-01</leafValues></_>
    <_>
      <internalNodes>
        0 -1 5816 -1331162919 -750452544 3 -109215537 9142507
        -1198882802 -2145288181 -95846331</internalNodes>
      <leafValues>
        -6.0552662611007690e-01 5.8155721426010132e-01</leafValues></_>
    <_>
      <internalNodes>
        0 -1 6098 -721396643 -653928047 268714051 -649752175 -1744266568
        -913792632 1497655724 1867174571</internalNodes>
      <leafValues>
        -5.6728434562683105e-01 6.2562811374664307e-01</leafValues></_></weakClassifiers></stage6>
</opencv_storage>
